fifo/rtl/fifo.v
module fifo(full,empty,halt,dout,din,rd,wr,rst,clr,clk);
output		full;
output		empty;
output		halt;
output[7:0]	dout;
input[7:0]	din;
input		rd;
input		wr;
input		rst;
input		clr;
input		clk;
reg[7:0]	mem[15:0];
reg[3:0]	cnt;
reg[3:0]	read_ptr,write_ptr;
reg[7:0]	dout;
always@(posedge clk or posedge rst)
begin
	if(rst)
	begin
		cnt<=4'b0;
		read_ptr<=4'b0;
		write_ptr<=4'b0;
	end
	else if(clr)
	begin
		cnt<=4'b0;
		read_ptr<=4'b0;
		write_ptr<=4'b0;
	end
	else 
		case({rd,wr})
			2'b10:
				begin	
					if(!empty)
					begin
						dout<=mem[read_ptr];
						read_ptr<=(read_ptr==4'b1111)?4'b0:(read_ptr+1'b1);
						cnt<=cnt-1'b1;
					end
				end
			2'b01:
				begin
					if(!full)
					begin
						mem[write_ptr]<=din;	
						write_ptr<=(write_ptr==4'b1111)?4'b0:(write_ptr+1'b1);
						cnt<=cnt+1'b1;
					end
				end
			2'b11:
				begin 
					mem[write_ptr]<=din;
					write_ptr<=(write_ptr==4'b1111)?4'b0:(write_ptr+1'b1);
					read_ptr<=(read_ptr==4'b1111)?4'b0:(read_ptr+1'b1);
					dout<=mem[read_ptr];
				end
		endcase
end
assign full=(cnt==4'b1111);
assign empty=(cnt==4'b0);
assign halt=(cnt==4'b111);
endmodule

fifo/bench/fifo_tb.v
`timescale 1ns/1ns
module fifo_tb;
wire		empty;
wire		full;
wire		halt;
wire[7:0]	dout;
reg[7:0]	din;
reg			rd;
reg			wr;
reg			rst;
reg			clr;
reg			clk;
integer		i;

fifo u0(.full(full),.empty(empty),.halt(halt),.dout(dout),.din(din),.rd(rd),.wr(wr),.rst(rst),.clr(clr),.clk(clk));

always #10 clk=~clk;
initial
begin
	i=0;
	clk=0;
	rst=0;
	clr=0;
	rd=0;
	wr=0;
	#1000;
	rst=1;
	#100;
	rst=0;
	#1000;
	clr=1;
	#100;
	clr=0;
	wr=1;
	while(!full)
	begin
		din=i;
		@(posedge clk);
		$display("wirte %d to position(%d)\n",din,u0.write_ptr);
		i=i+1;
	end
	wr=0;
	rd=1;
	while(!empty)
	begin
		@(posedge clk);
		$display("read %d form position(%d)\n",dout,u0.read_ptr);
	end
	rd=0;
	clr=0;
	i=0;
	#1000;
	wr=1;
	while(i<=3)
	begin
		din=i;
		@(posedge clk);
		$display("wirte %d to position(%d)\n",din,u0.write_ptr);
		i=i+1;
	end
	rd=1;
	while(i<=10)
	begin
		din=i;
		@(posedge clk);
		$display("wirte %d to position(%d)\n",din,u0.write_ptr);
		$display("read %d form position(%d)\n",dout,u0.read_ptr);
		i=i+1;
	end
	$finish;
end
always@(posedge clk)
begin
	if(empty && rd)
		$display("error read:operation read while fifo is empty\n");
	else if(full && wr)
		$display("error write:operation write while fifo is full\n");

end
	
initial 
	begin
		$dumpfile("../out/fifo.vcd");
		$dumpvars;
	end
endmodule

fifo/sim/out/fifo.vcd
$date
	Sat Jul 11 19:13:52 2015
$end
$version
	Icarus Verilog
$end
$timescale
	1ns
$end
$scope module fifo_tb $end
$var wire 8 ! dout [7:0] $end
$var wire 1 " empty $end
$var wire 1 # full $end
$var wire 1 $ halt $end
$var reg 1 % clk $end
$var reg 1 & clr $end
$var reg 8 ' din [7:0] $end
$var integer 32 ( i [31:0] $end
$var reg 1 ) rd $end
$var reg 1 * rst $end
$var reg 1 + wr $end
$scope module u0 $end
$var wire 1 , clk $end
$var wire 1 - clr $end
$var wire 8 . din [7:0] $end
$var wire 1 " empty $end
$var wire 1 # full $end
$var wire 1 $ halt $end
$var wire 1 / rd $end
$var wire 1 0 rst $end
$var wire 1 1 wr $end
$var reg 4 2 cnt [3:0] $end
$var reg 8 3 dout [7:0] $end
$var reg 4 4 read_ptr [3:0] $end
$var reg 4 5 write_ptr [3:0] $end
$upscope $end
$upscope $end
$enddefinitions $end
#0
$dumpvars
bx 5
bx 4
bx 3
bx 2
01
00
0/
bx .
0-
0,
0+
0*
0)
b0 (
bx '
0&
0%
x$
x#
x"
bx !
$end
#10
1%
1,
#20
0%
0,
#30
1%
1,
#40
0%
0,
#50
1%
1,
#60
0%
0,
#70
1%
1,
#80
0%
0,
#90
1%
1,
#100
0%
0,
#110
1%
1,
#120
0%
0,
#130
1%
1,
#140
0%
0,
#150
1%
1,
#160
0%
0,
#170
1%
1,
#180
0%
0,
#190
1%
1,
#200
0%
0,
#210
1%
1,
#220
0%
0,
#230
1%
1,
#240
0%
0,
#250
1%
1,
#260
0%
0,
#270
1%
1,
#280
0%
0,
#290
1%
1,
#300
0%
0,
#310
1%
1,
#320
0%
0,
#330
1%
1,
#340
0%
0,
#350
1%
1,
#360
0%
0,
#370
1%
1,
#380
0%
0,
#390
1%
1,
#400
0%
0,
#410
1%
1,
#420
0%
0,
#430
1%
1,
#440
0%
0,
#450
1%
1,
#460
0%
0,
#470
1%
1,
#480
0%
0,
#490
1%
1,
#500
0%
0,
#510
1%
1,
#520
0%
0,
#530
1%
1,
#540
0%
0,
#550
1%
1,
#560
0%
0,
#570
1%
1,
#580
0%
0,
#590
1%
1,
#600
0%
0,
#610
1%
1,
#620
0%
0,
#630
1%
1,
#640
0%
0,
#650
1%
1,
#660
0%
0,
#670
1%
1,
#680
0%
0,
#690
1%
1,
#700
0%
0,
#710
1%
1,
#720
0%
0,
#730
1%
1,
#740
0%
0,
#750
1%
1,
#760
0%
0,
#770
1%
1,
#780
0%
0,
#790
1%
1,
#800
0%
0,
#810
1%
1,
#820
0%
0,
#830
1%
1,
#840
0%
0,
#850
1%
1,
#860
0%
0,
#870
1%
1,
#880
0%
0,
#890
1%
1,
#900
0%
0,
#910
1%
1,
#920
0%
0,
#930
1%
1,
#940
0%
0,
#950
1%
1,
#960
0%
0,
#970
1%
1,
#980
0%
0,
#990
1%
1,
#1000
b0 5
b0 4
b0 2
0#
1"
0$
0%
0,
1*
10
#1010
1%
1,
#1020
0%
0,
#1030
1%
1,
#1040
0%
0,
#1050
1%
1,
#1060
0%
0,
#1070
1%
1,
#1080
0%
0,
#1090
1%
1,
#1100
0%
0,
0*
00
#1110
1%
1,
#1120
0%
0,
#1130
1%
1,
#1140
0%
0,
#1150
1%
1,
#1160
0%
0,
#1170
1%
1,
#1180
0%
0,
#1190
1%
1,
#1200
0%
0,
#1210
1%
1,
#1220
0%
0,
#1230
1%
1,
#1240
0%
0,
#1250
1%
1,
#1260
0%
0,
#1270
1%
1,
#1280
0%
0,
#1290
1%
1,
#1300
0%
0,
#1310
1%
1,
#1320
0%
0,
#1330
1%
1,
#1340
0%
0,
#1350
1%
1,
#1360
0%
0,
#1370
1%
1,
#1380
0%
0,
#1390
1%
1,
#1400
0%
0,
#1410
1%
1,
#1420
0%
0,
#1430
1%
1,
#1440
0%
0,
#1450
1%
1,
#1460
0%
0,
#1470
1%
1,
#1480
0%
0,
#1490
1%
1,
#1500
0%
0,
#1510
1%
1,
#1520
0%
0,
#1530
1%
1,
#1540
0%
0,
#1550
1%
1,
#1560
0%
0,
#1570
1%
1,
#1580
0%
0,
#1590
1%
1,
#1600
0%
0,
#1610
1%
1,
#1620
0%
0,
#1630
1%
1,
#1640
0%
0,
#1650
1%
1,
#1660
0%
0,
#1670
1%
1,
#1680
0%
0,
#1690
1%
1,
#1700
0%
0,
#1710
1%
1,
#1720
0%
0,
#1730
1%
1,
#1740
0%
0,
#1750
1%
1,
#1760
0%
0,
#1770
1%
1,
#1780
0%
0,
#1790
1%
1,
#1800
0%
0,
#1810
1%
1,
#1820
0%
0,
#1830
1%
1,
#1840
0%
0,
#1850
1%
1,
#1860
0%
0,
#1870
1%
1,
#1880
0%
0,
#1890
1%
1,
#1900
0%
0,
#1910
1%
1,
#1920
0%
0,
#1930
1%
1,
#1940
0%
0,
#1950
1%
1,
#1960
0%
0,
#1970
1%
1,
#1980
0%
0,
#1990
1%
1,
#2000
0%
0,
#2010
1%
1,
#2020
0%
0,
#2030
1%
1,
#2040
0%
0,
#2050
1%
1,
#2060
0%
0,
#2070
1%
1,
#2080
0%
0,
#2090
1%
1,
#2100
0%
0,
1&
1-
#2110
1%
1,
#2120
0%
0,
#2130
1%
1,
#2140
0%
0,
#2150
1%
1,
#2160
0%
0,
#2170
1%
1,
#2180
0%
0,
#2190
1%
1,
#2200
0%
0,
b0 '
b0 .
1+
11
0&
0-
#2210
b1 2
0"
b1 5
b1 '
b1 .
b1 (
1%
1,
#2220
0%
0,
#2230
b10 2
b10 5
b10 '
b10 .
b10 (
1%
1,
#2240
0%
0,
#2250
b11 2
b11 5
b11 '
b11 .
b11 (
1%
1,
#2260
0%
0,
#2270
b100 2
b100 5
b100 '
b100 .
b100 (
1%
1,
#2280
0%
0,
#2290
b101 2
b101 5
b101 '
b101 .
b101 (
1%
1,
#2300
0%
0,
#2310
b110 2
b110 5
b110 '
b110 .
b110 (
1%
1,
#2320
0%
0,
#2330
b111 2
1$
b111 5
b111 '
b111 .
b111 (
1%
1,
#2340
0%
0,
#2350
b1000 2
0$
b1000 5
b1000 '
b1000 .
b1000 (
1%
1,
#2360
0%
0,
#2370
b1001 2
b1001 5
b1001 '
b1001 .
b1001 (
1%
1,
#2380
0%
0,
#2390
b1010 2
b1010 5
b1010 '
b1010 .
b1010 (
1%
1,
#2400
0%
0,
#2410
b1011 2
b1011 5
b1011 '
b1011 .
b1011 (
1%
1,
#2420
0%
0,
#2430
b1100 2
b1100 5
b1100 '
b1100 .
b1100 (
1%
1,
#2440
0%
0,
#2450
b1101 2
b1101 5
b1101 '
b1101 .
b1101 (
1%
1,
#2460
0%
0,
#2470
b1110 2
b1110 5
b1110 '
b1110 .
b1110 (
1%
1,
#2480
0%
0,
#2490
b1111 2
1#
b1111 5
b1111 '
b1111 .
b1111 (
1%
1,
#2500
0%
0,
#2510
b1110 2
0#
b1 4
b1 3
b1 !
1)
1/
0+
01
b10000 (
1%
1,
#2520
0%
0,
#2530
b1101 2
b10 4
b10 3
b10 !
1%
1,
#2540
0%
0,
#2550
b1100 2
b11 4
b11 3
b11 !
1%
1,
#2560
0%
0,
#2570
b1011 2
b100 4
b100 3
b100 !
1%
1,
#2580
0%
0,
#2590
b1010 2
b101 4
b101 3
b101 !
1%
1,
#2600
0%
0,
#2610
b1001 2
b110 4
b110 3
b110 !
1%
1,
#2620
0%
0,
#2630
b1000 2
b111 4
b111 3
b111 !
1%
1,
#2640
0%
0,
#2650
b111 2
1$
b1000 4
b1000 3
b1000 !
1%
1,
#2660
0%
0,
#2670
b110 2
0$
b1001 4
b1001 3
b1001 !
1%
1,
#2680
0%
0,
#2690
b101 2
b1010 4
b1010 3
b1010 !
1%
1,
#2700
0%
0,
#2710
b100 2
b1011 4
b1011 3
b1011 !
1%
1,
#2720
0%
0,
#2730
b11 2
b1100 4
b1100 3
b1100 !
1%
1,
#2740
0%
0,
#2750
b10 2
b1101 4
b1101 3
b1101 !
1%
1,
#2760
0%
0,
#2770
b1 2
b1110 4
b1110 3
b1110 !
1%
1,
#2780
0%
0,
#2790
b0 2
1"
b1111 4
b1111 3
b1111 !
1%
1,
#2800
0%
0,
#2810
b0 (
0)
0/
1%
1,
