shift/rtl/shift_rtl/shift_rtl.v
module shift(data_out,data_in,shift,right,arith);
output[31:0] data_out;
input[31:0]  data_in;
input[4:0]   shift;
input		 right;
//arith=1 arith shift arith=0 logic shift
input		 arith;
wire		 sign=data_in[31]&arith;
wire[15:0]   high16={16{sign}};
wire[31:0]	 data_sl16,data_sl8,data_sl4,data_sl2,data_sl1;
wire[31:0]	 data_sr16,data_sr8,data_sr4,data_sr2,data_sr1;
wire[31:0]	 data_s16 ,data_s8 ,data_s4 ,data_s2 ,data_s1 ;
wire[31:0]	 data_r16 ,data_r8 ,data_r4 ,data_r2;
//shift 16
assign data_sl16={data_in[15:0],16'b0};
assign data_sr16={high16,data_in[31:16]};
mux32 u16(.out(data_s16),.a(data_sr16),.b(data_sl16),.sel(right));
mux32 us0(.out(data_r16),.a(data_s16),.b(data_in),.sel(shift[4]));
//shift 8
assign data_sl8={data_r16[23:0],8'b0};
assign data_sr8={high16[7:0],data_r16[31:8]};
mux32 u8(.out(data_s8),.a(data_sr8),.b(data_sl8),.sel(right));
mux32 us1(.out(data_r8),.a(data_s8),.b(data_r16),.sel(shift[3]));
//shift 4
assign data_sl4={data_r8[27:0],4'b0};
assign data_sr4={high16[3:0],data_r8[31:4]};
mux32 u4(.out(data_s4),.a(data_sr4),.b(data_sl4),.sel(right));
mux32 us2(.out(data_r4),.a(data_s4),.b(data_r8),.sel(shift[2]));
//shift 2
assign data_sl2={data_r4[29:0],2'b0};
assign data_sr2={high16[1:0],data_r4[31:2]};
mux32 u2(.out(data_s2),.a(data_sr2),.b(data_sl2),.sel(right));
mux32 us3(.out(data_r2),.a(data_s2),.b(data_r4),.sel(shift[1]));
//shift 1
assign data_sl1={data_r2[30:0],1'b0};
assign data_sr1={high16[0],data_r16[31:1]};
mux32 u1(.out(data_s1),.a(data_sr1),.b(data_sl1),.sel(right));
mux32 us4(.out(data_out),.a(data_s1),.b(data_r2),.sel(shift[0]));
endmodule

module mux32(out,a,b,sel);
output[31:0] out;
input[31:0]  a;
input[31:0]  b;
input		 sel;

assign out=sel?a:b;

endmodule

shift/bench/shift_tb.v
`timescale 1ns/1ns
module shift_tb;
wire[31:0] data_out;
reg[31:0]  data_in;
reg[4:0]   shift;
reg		   right;
reg		   arith;
//module define
shift u0(.data_out(data_out),.data_in(data_in),.shift(shift),.right(right),.arith(arith));
//generate input signal
reg[1:0] arith_r,right_r;
reg[6:0] shift_r;
initial
begin
	data_in<=32'b1010_1010_1010_1010_1010_1010_1010_1010;
	for(arith_r=2'b0;arith_r<=2'b1;arith_r=arith_r+1)
	begin
		arith<=arith_r[0];
		for(right_r=2'b0;right_r<=2'b1;right_r=right_r+1)
		begin
			right<=right_r[0];
			for(shift_r=6'b0;shift_r<=6'b11111;shift_r=shift_r+1'b1)
			begin
				shift<=shift_r[4:0];
				$display("\tdata_out=%b,shift=%b,arith=%b,right=%b,data_in=%b\n",data_out,shift,arith,right,data_in);
				#100;
				data_in<=32'b1010_1010_1010_1010_1010_1010_1010_1010;
			end
		end
	end
end

initial 
begin
	$dumpfile("../out/shift.vcd");
	$dumpvars;
end
endmodule

shift/sim/out/shift.vcd
$date
	Fri Jul 10 11:31:04 2015
$end
$version
	Icarus Verilog
$end
$timescale
	1ns
$end
$scope module shift_tb $end
$var wire 32 ! data_out [31:0] $end
$var reg 1 " arith $end
$var reg 2 # arith_r [1:0] $end
$var reg 32 $ data_in [31:0] $end
$var reg 1 % right $end
$var reg 2 & right_r [1:0] $end
$var reg 5 ' shift [4:0] $end
$var reg 7 ( shift_r [6:0] $end
$scope module u0 $end
$var wire 1 ) arith $end
$var wire 32 * data_in [31:0] $end
$var wire 32 + data_out [31:0] $end
$var wire 32 , data_r16 [31:0] $end
$var wire 32 - data_r2 [31:0] $end
$var wire 32 . data_r4 [31:0] $end
$var wire 32 / data_r8 [31:0] $end
$var wire 32 0 data_s1 [31:0] $end
$var wire 32 1 data_s16 [31:0] $end
$var wire 32 2 data_s2 [31:0] $end
$var wire 32 3 data_s4 [31:0] $end
$var wire 32 4 data_s8 [31:0] $end
$var wire 32 5 data_sl1 [31:0] $end
$var wire 32 6 data_sl16 [31:0] $end
$var wire 32 7 data_sl2 [31:0] $end
$var wire 32 8 data_sl4 [31:0] $end
$var wire 32 9 data_sl8 [31:0] $end
$var wire 32 : data_sr1 [31:0] $end
$var wire 32 ; data_sr16 [31:0] $end
$var wire 32 < data_sr2 [31:0] $end
$var wire 32 = data_sr4 [31:0] $end
$var wire 32 > data_sr8 [31:0] $end
$var wire 16 ? high16 [15:0] $end
$var wire 1 @ right $end
$var wire 5 A shift [4:0] $end
$var wire 1 B sign $end
$scope module u16 $end
$var wire 32 C a [31:0] $end
$var wire 32 D b [31:0] $end
$var wire 32 E out [31:0] $end
$var wire 1 @ sel $end
$upscope $end
$scope module us0 $end
$var wire 32 F a [31:0] $end
$var wire 32 G b [31:0] $end
$var wire 32 H out [31:0] $end
$var wire 1 I sel $end
$upscope $end
$scope module u8 $end
$var wire 32 J a [31:0] $end
$var wire 32 K b [31:0] $end
$var wire 32 L out [31:0] $end
$var wire 1 @ sel $end
$upscope $end
$scope module us1 $end
$var wire 32 M a [31:0] $end
$var wire 32 N b [31:0] $end
$var wire 32 O out [31:0] $end
$var wire 1 P sel $end
$upscope $end
$scope module u4 $end
$var wire 32 Q a [31:0] $end
$var wire 32 R b [31:0] $end
$var wire 32 S out [31:0] $end
$var wire 1 @ sel $end
$upscope $end
$scope module us2 $end
$var wire 32 T a [31:0] $end
$var wire 32 U b [31:0] $end
$var wire 32 V out [31:0] $end
$var wire 1 W sel $end
$upscope $end
$scope module u2 $end
$var wire 32 X a [31:0] $end
$var wire 32 Y b [31:0] $end
$var wire 32 Z out [31:0] $end
$var wire 1 @ sel $end
$upscope $end
$scope module us3 $end
$var wire 32 [ a [31:0] $end
$var wire 32 \ b [31:0] $end
$var wire 32 ] out [31:0] $end
$var wire 1 ^ sel $end
$upscope $end
$scope module u1 $end
$var wire 32 _ a [31:0] $end
$var wire 32 ` b [31:0] $end
$var wire 32 a out [31:0] $end
$var wire 1 @ sel $end
$upscope $end
$scope module us4 $end
$var wire 32 b a [31:0] $end
$var wire 32 c b [31:0] $end
$var wire 32 d out [31:0] $end
$var wire 1 e sel $end
$upscope $end
$upscope $end
$upscope $end
$enddefinitions $end
#0
$dumpvars
0e
b10101010101010101010101010101010 d
b10101010101010101010101010101010 c
b1010101010101010101010101010100 b
b1010101010101010101010101010100 a
b1010101010101010101010101010100 `
b1010101010101010101010101010101 _
0^
b10101010101010101010101010101010 ]
b10101010101010101010101010101010 \
b10101010101010101010101010101000 [
b10101010101010101010101010101000 Z
b10101010101010101010101010101000 Y
b101010101010101010101010101010 X
0W
b10101010101010101010101010101010 V
b10101010101010101010101010101010 U
b10101010101010101010101010100000 T
b10101010101010101010101010100000 S
b10101010101010101010101010100000 R
b1010101010101010101010101010 Q
0P
b10101010101010101010101010101010 O
b10101010101010101010101010101010 N
b10101010101010101010101000000000 M
b10101010101010101010101000000000 L
b10101010101010101010101000000000 K
b101010101010101010101010 J
0I
b10101010101010101010101010101010 H
b10101010101010101010101010101010 G
b10101010101010100000000000000000 F
b10101010101010100000000000000000 E
b10101010101010100000000000000000 D
b1010101010101010 C
0B
b0 A
0@
b0 ?
b101010101010101010101010 >
b1010101010101010101010101010 =
b101010101010101010101010101010 <
b1010101010101010 ;
b1010101010101010101010101010101 :
b10101010101010101010101000000000 9
b10101010101010101010101010100000 8
b10101010101010101010101010101000 7
b10101010101010100000000000000000 6
b1010101010101010101010101010100 5
b10101010101010101010101000000000 4
b10101010101010101010101010100000 3
b10101010101010101010101010101000 2
b10101010101010100000000000000000 1
b1010101010101010101010101010100 0
b10101010101010101010101010101010 /
b10101010101010101010101010101010 .
b10101010101010101010101010101010 -
b10101010101010101010101010101010 ,
b10101010101010101010101010101010 +
b10101010101010101010101010101010 *
0)
b0 (
b0 '
b0 &
0%
b10101010101010101010101010101010 $
b0 #
0"
b10101010101010101010101010101010 !
$end
#100
b1010101010101010101010101010100 !
b1010101010101010101010101010100 +
b1010101010101010101010101010100 d
1e
b1 '
b1 A
b1 (
#200
b1010101010101010101010101010000 0
b1010101010101010101010101010000 a
b1010101010101010101010101010000 b
b1010101010101010101010101010000 5
b1010101010101010101010101010000 `
b10101010101010101010101010101000 -
b10101010101010101010101010101000 ]
b10101010101010101010101010101000 c
b10101010101010101010101010101000 !
b10101010101010101010101010101000 +
b10101010101010101010101010101000 d
1^
0e
b10 '
b10 A
b10 (
#300
b1010101010101010101010101010000 !
b1010101010101010101010101010000 +
b1010101010101010101010101010000 d
1e
b11 '
b11 A
b11 (
#400
b10101010101010101010101010000000 2
b10101010101010101010101010000000 Z
b10101010101010101010101010000000 [
b1010101010101010101010101000000 0
b1010101010101010101010101000000 a
b1010101010101010101010101000000 b
b101010101010101010101010101000 <
b101010101010101010101010101000 X
b10101010101010101010101010000000 7
b10101010101010101010101010000000 Y
b1010101010101010101010101000000 5
b1010101010101010101010101000000 `
b10101010101010101010101010100000 .
b10101010101010101010101010100000 V
b10101010101010101010101010100000 \
b10101010101010101010101010100000 -
b10101010101010101010101010100000 ]
b10101010101010101010101010100000 c
b10101010101010101010101010100000 !
b10101010101010101010101010100000 +
b10101010101010101010101010100000 d
1W
0^
0e
b100 '
b100 A
b100 (
#500
b1010101010101010101010101000000 !
b1010101010101010101010101000000 +
b1010101010101010101010101000000 d
1e
b101 '
b101 A
b101 (
#600
b1010101010101010101010100000000 0
b1010101010101010101010100000000 a
b1010101010101010101010100000000 b
b1010101010101010101010100000000 5
b1010101010101010101010100000000 `
b10101010101010101010101010000000 -
b10101010101010101010101010000000 ]
b10101010101010101010101010000000 c
b10101010101010101010101010000000 !
b10101010101010101010101010000000 +
b10101010101010101010101010000000 d
1^
0e
b110 '
b110 A
b110 (
#700
b1010101010101010101010100000000 !
b1010101010101010101010100000000 +
b1010101010101010101010100000000 d
1e
b111 '
b111 A
b111 (
#800
b10101010101010101010000000000000 3
b10101010101010101010000000000000 S
b10101010101010101010000000000000 T
b10101010101010101010100000000000 2
b10101010101010101010100000000000 Z
b10101010101010101010100000000000 [
b1010101010101010101010000000000 0
b1010101010101010101010000000000 a
b1010101010101010101010000000000 b
b1010101010101010101010100000 =
b1010101010101010101010100000 Q
b10101010101010101010000000000000 8
b10101010101010101010000000000000 R
b101010101010101010101010000000 <
b101010101010101010101010000000 X
b10101010101010101010100000000000 7
b10101010101010101010100000000000 Y
b1010101010101010101010000000000 5
b1010101010101010101010000000000 `
b10101010101010101010101000000000 /
b10101010101010101010101000000000 O
b10101010101010101010101000000000 U
b10101010101010101010101000000000 .
b10101010101010101010101000000000 V
b10101010101010101010101000000000 \
b10101010101010101010101000000000 -
b10101010101010101010101000000000 ]
b10101010101010101010101000000000 c
b10101010101010101010101000000000 !
b10101010101010101010101000000000 +
b10101010101010101010101000000000 d
1P
0W
0^
0e
b1000 '
b1000 A
b1000 (
#900
b1010101010101010101010000000000 !
b1010101010101010101010000000000 +
b1010101010101010101010000000000 d
1e
b1001 '
b1001 A
b1001 (
#1000
b1010101010101010101000000000000 0
b1010101010101010101000000000000 a
b1010101010101010101000000000000 b
b1010101010101010101000000000000 5
b1010101010101010101000000000000 `
b10101010101010101010100000000000 -
b10101010101010101010100000000000 ]
b10101010101010101010100000000000 c
b10101010101010101010100000000000 !
b10101010101010101010100000000000 +
b10101010101010101010100000000000 d
1^
0e
b1010 '
b1010 A
b1010 (
#1100
b1010101010101010101000000000000 !
b1010101010101010101000000000000 +
b1010101010101010101000000000000 d
1e
b1011 '
b1011 A
b1011 (
#1200
b10101010101010101000000000000000 2
b10101010101010101000000000000000 Z
b10101010101010101000000000000000 [
b1010101010101010100000000000000 0
b1010101010101010100000000000000 a
b1010101010101010100000000000000 b
b101010101010101010100000000000 <
b101010101010101010100000000000 X
b10101010101010101000000000000000 7
b10101010101010101000000000000000 Y
b1010101010101010100000000000000 5
b1010101010101010100000000000000 `
b10101010101010101010000000000000 .
b10101010101010101010000000000000 V
b10101010101010101010000000000000 \
b10101010101010101010000000000000 -
b10101010101010101010000000000000 ]
b10101010101010101010000000000000 c
b10101010101010101010000000000000 !
b10101010101010101010000000000000 +
b10101010101010101010000000000000 d
1W
0^
0e
b1100 '
b1100 A
b1100 (
#1300
b1010101010101010100000000000000 !
b1010101010101010100000000000000 +
b1010101010101010100000000000000 d
1e
b1101 '
b1101 A
b1101 (
#1400
b1010101010101010000000000000000 0
b1010101010101010000000000000000 a
b1010101010101010000000000000000 b
b1010101010101010000000000000000 5
b1010101010101010000000000000000 `
b10101010101010101000000000000000 -
b10101010101010101000000000000000 ]
b10101010101010101000000000000000 c
b10101010101010101000000000000000 !
b10101010101010101000000000000000 +
b10101010101010101000000000000000 d
1^
0e
b1110 '
b1110 A
b1110 (
#1500
b1010101010101010000000000000000 !
b1010101010101010000000000000000 +
b1010101010101010000000000000000 d
1e
b1111 '
b1111 A
b1111 (
#1600
b10101010000000000000000000000000 4
b10101010000000000000000000000000 L
b10101010000000000000000000000000 M
b10101010101000000000000000000000 3
b10101010101000000000000000000000 S
b10101010101000000000000000000000 T
b10101010101010000000000000000000 2
b10101010101010000000000000000000 Z
b10101010101010000000000000000000 [
b1010101010101000000000000000000 0
b1010101010101000000000000000000 a
b1010101010101000000000000000000 b
b1010101010101010000000000000000 :
b1010101010101010000000000000000 _
b101010101010101000000000 >
b101010101010101000000000 J
b10101010000000000000000000000000 9
b10101010000000000000000000000000 K
b1010101010101010000000000000 =
b1010101010101010000000000000 Q
b10101010101000000000000000000000 8
b10101010101000000000000000000000 R
b101010101010101000000000000000 <
b101010101010101000000000000000 X
b10101010101010000000000000000000 7
b10101010101010000000000000000000 Y
b1010101010101000000000000000000 5
b1010101010101000000000000000000 `
b10101010101010100000000000000000 ,
b10101010101010100000000000000000 H
b10101010101010100000000000000000 N
b10101010101010100000000000000000 /
b10101010101010100000000000000000 O
b10101010101010100000000000000000 U
b10101010101010100000000000000000 .
b10101010101010100000000000000000 V
b10101010101010100000000000000000 \
b10101010101010100000000000000000 -
b10101010101010100000000000000000 ]
b10101010101010100000000000000000 c
b10101010101010100000000000000000 !
b10101010101010100000000000000000 +
b10101010101010100000000000000000 d
1I
0P
0W
0^
0e
b10000 '
b10000 A
b10000 (
#1700
b1010101010101000000000000000000 !
b1010101010101000000000000000000 +
b1010101010101000000000000000000 d
1e
b10001 '
b10001 A
b10001 (
#1800
b1010101010100000000000000000000 0
b1010101010100000000000000000000 a
b1010101010100000000000000000000 b
b1010101010100000000000000000000 5
b1010101010100000000000000000000 `
b10101010101010000000000000000000 -
b10101010101010000000000000000000 ]
b10101010101010000000000000000000 c
b10101010101010000000000000000000 !
b10101010101010000000000000000000 +
b10101010101010000000000000000000 d
1^
0e
b10010 '
b10010 A
b10010 (
#1900
b1010101010100000000000000000000 !
b1010101010100000000000000000000 +
b1010101010100000000000000000000 d
1e
b10011 '
b10011 A
b10011 (
#2000
b10101010100000000000000000000000 2
b10101010100000000000000000000000 Z
b10101010100000000000000000000000 [
b1010101010000000000000000000000 0
b1010101010000000000000000000000 a
b1010101010000000000000000000000 b
b101010101010000000000000000000 <
b101010101010000000000000000000 X
b10101010100000000000000000000000 7
b10101010100000000000000000000000 Y
b1010101010000000000000000000000 5
b1010101010000000000000000000000 `
b10101010101000000000000000000000 .
b10101010101000000000000000000000 V
b10101010101000000000000000000000 \
b10101010101000000000000000000000 -
b10101010101000000000000000000000 ]
b10101010101000000000000000000000 c
b10101010101000000000000000000000 !
b10101010101000000000000000000000 +
b10101010101000000000000000000000 d
1W
0^
0e
b10100 '
b10100 A
b10100 (
#2100
b1010101010000000000000000000000 !
b1010101010000000000000000000000 +
b1010101010000000000000000000000 d
1e
b10101 '
b10101 A
b10101 (
#2200
b1010101000000000000000000000000 0
b1010101000000000000000000000000 a
b1010101000000000000000000000000 b
b1010101000000000000000000000000 5
b1010101000000000000000000000000 `
b10101010100000000000000000000000 -
b10101010100000000000000000000000 ]
b10101010100000000000000000000000 c
b10101010100000000000000000000000 !
b10101010100000000000000000000000 +
b10101010100000000000000000000000 d
1^
0e
b10110 '
b10110 A
b10110 (
#2300
b1010101000000000000000000000000 !
b1010101000000000000000000000000 +
b1010101000000000000000000000000 d
1e
b10111 '
b10111 A
b10111 (
#2400
b10100000000000000000000000000000 3
b10100000000000000000000000000000 S
b10100000000000000000000000000000 T
b10101000000000000000000000000000 2
b10101000000000000000000000000000 Z
b10101000000000000000000000000000 [
b1010100000000000000000000000000 0
b1010100000000000000000000000000 a
b1010100000000000000000000000000 b
b1010101000000000000000000000 =
b1010101000000000000000000000 Q
b10100000000000000000000000000000 8
b10100000000000000000000000000000 R
b101010100000000000000000000000 <
b101010100000000000000000000000 X
b10101000000000000000000000000000 7
b10101000000000000000000000000000 Y
b1010100000000000000000000000000 5
b1010100000000000000000000000000 `
b10101010000000000000000000000000 /
b10101010000000000000000000000000 O
b10101010000000000000000000000000 U
b10101010000000000000000000000000 .
b10101010000000000000000000000000 V
b10101010000000000000000000000000 \
b10101010000000000000000000000000 -
b10101010000000000000000000000000 ]
b10101010000000000000000000000000 c
b10101010000000000000000000000000 !
b10101010000000000000000000000000 +
b10101010000000000000000000000000 d
1P
0W
0^
0e
b11000 '
b11000 A
b11000 (
#2500
b1010100000000000000000000000000 !
b1010100000000000000000000000000 +
b1010100000000000000000000000000 d
1e
b11001 '
b11001 A
b11001 (
#2600
b1010000000000000000000000000000 0
b1010000000000000000000000000000 a
b1010000000000000000000000000000 b
b1010000000000000000000000000000 5
b1010000000000000000000000000000 `
b10101000000000000000000000000000 -
b10101000000000000000000000000000 ]
b10101000000000000000000000000000 c
b10101000000000000000000000000000 !
b10101000000000000000000000000000 +
b10101000000000000000000000000000 d
1^
0e
b11010 '
b11010 A
b11010 (
#2700
b1010000000000000000000000000000 !
b1010000000000000000000000000000 +
b1010000000000000000000000000000 d
1e
b11011 '
b11011 A
b11011 (
#2800
b10000000000000000000000000000000 2
b10000000000000000000000000000000 Z
b10000000000000000000000000000000 [
b1000000000000000000000000000000 0
b1000000000000000000000000000000 a
b1000000000000000000000000000000 b
b101000000000000000000000000000 <
b101000000000000000000000000000 X
b10000000000000000000000000000000 7
b10000000000000000000000000000000 Y
b1000000000000000000000000000000 5
b1000000000000000000000000000000 `
b10100000000000000000000000000000 .
b10100000000000000000000000000000 V
b10100000000000000000000000000000 \
b10100000000000000000000000000000 -
b10100000000000000000000000000000 ]
b10100000000000000000000000000000 c
b10100000000000000000000000000000 !
b10100000000000000000000000000000 +
b10100000000000000000000000000000 d
1W
0^
0e
b11100 '
b11100 A
b11100 (
#2900
b1000000000000000000000000000000 !
b1000000000000000000000000000000 +
b1000000000000000000000000000000 d
1e
b11101 '
b11101 A
b11101 (
#3000
b0 0
b0 a
b0 b
b0 5
b0 `
b10000000000000000000000000000000 -
b10000000000000000000000000000000 ]
b10000000000000000000000000000000 c
b10000000000000000000000000000000 !
b10000000000000000000000000000000 +
b10000000000000000000000000000000 d
1^
0e
b11110 '
b11110 A
b11110 (
#3100
b0 !
b0 +
b0 d
1e
b11111 '
b11111 A
b11111 (
#3200
b1010101010101010101010101010101 :
b1010101010101010101010101010101 _
b101010101010101010101010 >
b101010101010101010101010 J
b10101010101010101010101000000000 9
b10101010101010101010101000000000 K
b1010101010101010101010101010 =
b1010101010101010101010101010 Q
b10101010101010101010101010100000 8
b10101010101010101010101010100000 R
b101010101010101010101010101010 <
b101010101010101010101010101010 X
b10101010101010101010101010101000 7
b10101010101010101010101010101000 Y
b1010101010101010101010101010100 5
b1010101010101010101010101010100 `
b10101010101010101010101010101010 ,
b10101010101010101010101010101010 H
b10101010101010101010101010101010 N
b10101010101010101010101010101010 /
b10101010101010101010101010101010 O
b10101010101010101010101010101010 U
b10101010101010101010101010101010 .
b10101010101010101010101010101010 V
b10101010101010101010101010101010 \
b10101010101010101010101010101010 -
b10101010101010101010101010101010 ]
b10101010101010101010101010101010 c
b10101010101010101010101010101010 !
b10101010101010101010101010101010 +
b10101010101010101010101010101010 d
0I
0P
0W
0^
0e
b1010101010101010 1
b1010101010101010 E
b1010101010101010 F
b101010101010101010101010 4
b101010101010101010101010 L
b101010101010101010101010 M
b1010101010101010101010101010 3
b1010101010101010101010101010 S
b1010101010101010101010101010 T
b101010101010101010101010101010 2
b101010101010101010101010101010 Z
b101010101010101010101010101010 [
b1010101010101010101010101010101 0
b1010101010101010101010101010101 a
b1010101010101010101010101010101 b
b0 '
b0 A
1%
1@
b1 &
b0 (
#3300
b1010101010101010101010101010101 !
b1010101010101010101010101010101 +
b1010101010101010101010101010101 d
1e
b1 '
b1 A
b1 (
#3400
b101010101010101010101010101010 -
b101010101010101010101010101010 ]
b101010101010101010101010101010 c
b101010101010101010101010101010 !
b101010101010101010101010101010 +
b101010101010101010101010101010 d
1^
0e
b10 '
b10 A
b10 (
#3500
b1010101010101010101010101010101 !
b1010101010101010101010101010101 +
b1010101010101010101010101010101 d
1e
b11 '
b11 A
b11 (
#3600
b10101010101010101010101010100 5
b10101010101010101010101010100 `
b10101010101010101010101010 2
b10101010101010101010101010 Z
b10101010101010101010101010 [
b10101010101010101010101010 <
b10101010101010101010101010 X
b101010101010101010101010101000 7
b101010101010101010101010101000 Y
b1010101010101010101010101010 .
b1010101010101010101010101010 V
b1010101010101010101010101010 \
b1010101010101010101010101010 -
b1010101010101010101010101010 ]
b1010101010101010101010101010 c
b1010101010101010101010101010 !
b1010101010101010101010101010 +
b1010101010101010101010101010 d
1W
0^
0e
b100 '
b100 A
b100 (
#3700
b1010101010101010101010101010101 !
b1010101010101010101010101010101 +
b1010101010101010101010101010101 d
1e
b101 '
b101 A
b101 (
#3800
b101010101010101010101010100 5
b101010101010101010101010100 `
b10101010101010101010101010 -
b10101010101010101010101010 ]
b10101010101010101010101010 c
b10101010101010101010101010 !
b10101010101010101010101010 +
b10101010101010101010101010 d
1^
0e
b110 '
b110 A
b110 (
#3900
b1010101010101010101010101010101 !
b1010101010101010101010101010101 +
b1010101010101010101010101010101 d
1e
b111 '
b111 A
b111 (
#4000
b10101010101010101010 3
b10101010101010101010 S
b10101010101010101010 T
b1010101010101010101010 2
b1010101010101010101010 Z
b1010101010101010101010 [
b10101010101010101010 =
b10101010101010101010 Q
b1010101010101010101010100000 8
b1010101010101010101010100000 R
b1010101010101010101010 <
b1010101010101010101010 X
b10101010101010101010101000 7
b10101010101010101010101000 Y
b1010101010101010101010100 5
b1010101010101010101010100 `
b101010101010101010101010 /
b101010101010101010101010 O
b101010101010101010101010 U
b101010101010101010101010 .
b101010101010101010101010 V
b101010101010101010101010 \
b101010101010101010101010 -
b101010101010101010101010 ]
b101010101010101010101010 c
b101010101010101010101010 !
b101010101010101010101010 +
b101010101010101010101010 d
1P
0W
0^
0e
b1000 '
b1000 A
b1000 (
#4100
b1010101010101010101010101010101 !
b1010101010101010101010101010101 +
b1010101010101010101010101010101 d
1e
b1001 '
b1001 A
b1001 (
#4200
b10101010101010101010100 5
b10101010101010101010100 `
b1010101010101010101010 -
b1010101010101010101010 ]
b1010101010101010101010 c
b1010101010101010101010 !
b1010101010101010101010 +
b1010101010101010101010 d
1^
0e
b1010 '
b1010 A
b1010 (
#4300
b1010101010101010101010101010101 !
b1010101010101010101010101010101 +
b1010101010101010101010101010101 d
1e
b1011 '
b1011 A
b1011 (
#4400
b101010101010101010 2
b101010101010101010 Z
b101010101010101010 [
b101010101010101010 <
b101010101010101010 X
b1010101010101010101000 7
b1010101010101010101000 Y
b101010101010101010100 5
b101010101010101010100 `
b10101010101010101010 .
b10101010101010101010 V
b10101010101010101010 \
b10101010101010101010 -
b10101010101010101010 ]
b10101010101010101010 c
b10101010101010101010 !
b10101010101010101010 +
b10101010101010101010 d
1W
0^
0e
b1100 '
b1100 A
b1100 (
#4500
b1010101010101010101010101010101 !
b1010101010101010101010101010101 +
b1010101010101010101010101010101 d
1e
b1101 '
b1101 A
b1101 (
#4600
b1010101010101010100 5
b1010101010101010100 `
b101010101010101010 -
b101010101010101010 ]
b101010101010101010 c
b101010101010101010 !
b101010101010101010 +
b101010101010101010 d
1^
0e
b1110 '
b1110 A
b1110 (
#4700
b1010101010101010101010101010101 !
b1010101010101010101010101010101 +
b1010101010101010101010101010101 d
1e
b1111 '
b1111 A
b1111 (
#4800
b101010101010101 0
b101010101010101 a
b101010101010101 b
b10101010 4
b10101010 L
b10101010 M
b101010101010 3
b101010101010 S
b101010101010 T
b10101010101010 2
b10101010101010 Z
b10101010101010 [
b101010101010101 :
b101010101010101 _
b10101010 >
b10101010 J
b101010101010101000000000 9
b101010101010101000000000 K
b101010101010 =
b101010101010 Q
b10101010101010100000 8
b10101010101010100000 R
b10101010101010 <
b10101010101010 X
b101010101010101000 7
b101010101010101000 Y
b10101010101010100 5
b10101010101010100 `
b1010101010101010 ,
b1010101010101010 H
b1010101010101010 N
b1010101010101010 /
b1010101010101010 O
b1010101010101010 U
b1010101010101010 .
b1010101010101010 V
b1010101010101010 \
b1010101010101010 -
b1010101010101010 ]
b1010101010101010 c
b1010101010101010 !
b1010101010101010 +
b1010101010101010 d
1I
0P
0W
0^
0e
b10000 '
b10000 A
b10000 (
#4900
b101010101010101 !
b101010101010101 +
b101010101010101 d
1e
b10001 '
b10001 A
b10001 (
#5000
b101010101010100 5
b101010101010100 `
b10101010101010 -
b10101010101010 ]
b10101010101010 c
b10101010101010 !
b10101010101010 +
b10101010101010 d
1^
0e
b10010 '
b10010 A
b10010 (
#5100
b101010101010101 !
b101010101010101 +
b101010101010101 d
1e
b10011 '
b10011 A
b10011 (
#5200
b1010101010 2
b1010101010 Z
b1010101010 [
b1010101010 <
b1010101010 X
b10101010101000 7
b10101010101000 Y
b1010101010100 5
b1010101010100 `
b101010101010 .
b101010101010 V
b101010101010 \
b101010101010 -
b101010101010 ]
b101010101010 c
b101010101010 !
b101010101010 +
b101010101010 d
1W
0^
0e
b10100 '
b10100 A
b10100 (
#5300
b101010101010101 !
b101010101010101 +
b101010101010101 d
1e
b10101 '
b10101 A
b10101 (
#5400
b10101010100 5
b10101010100 `
b1010101010 -
b1010101010 ]
b1010101010 c
b1010101010 !
b1010101010 +
b1010101010 d
1^
0e
b10110 '
b10110 A
b10110 (
#5500
b101010101010101 !
b101010101010101 +
b101010101010101 d
1e
b10111 '
b10111 A
b10111 (
#5600
b1010 3
b1010 S
b1010 T
b101010 2
b101010 Z
b101010 [
b1010 =
b1010 Q
b101010100000 8
b101010100000 R
b101010 <
b101010 X
b1010101000 7
b1010101000 Y
b101010100 5
b101010100 `
b10101010 /
b10101010 O
b10101010 U
b10101010 .
b10101010 V
b10101010 \
b10101010 -
b10101010 ]
b10101010 c
b10101010 !
b10101010 +
b10101010 d
1P
0W
0^
0e
b11000 '
b11000 A
b11000 (
#5700
b101010101010101 !
b101010101010101 +
b101010101010101 d
1e
b11001 '
b11001 A
b11001 (
#5800
b1010100 5
b1010100 `
b101010 -
b101010 ]
b101010 c
b101010 !
b101010 +
b101010 d
1^
0e
b11010 '
b11010 A
b11010 (
#5900
b101010101010101 !
b101010101010101 +
b101010101010101 d
1e
b11011 '
b11011 A
b11011 (
#6000
b10 2
b10 Z
b10 [
b10 <
b10 X
b101000 7
b101000 Y
b10100 5
b10100 `
b1010 .
b1010 V
b1010 \
b1010 -
b1010 ]
b1010 c
b1010 !
b1010 +
b1010 d
1W
0^
0e
b11100 '
b11100 A
b11100 (
#6100
b101010101010101 !
b101010101010101 +
b101010101010101 d
1e
b11101 '
b11101 A
b11101 (
#6200
b100 5
b100 `
b10 -
b10 ]
b10 c
b10 !
b10 +
b10 d
1^
0e
b11110 '
b11110 A
b11110 (
#6300
b101010101010101 !
b101010101010101 +
b101010101010101 d
1e
b11111 '
b11111 A
b11111 (
#6400
b10101010101010101010101000000000 9
b10101010101010101010101000000000 K
b10101010101010101010101010100000 8
b10101010101010101010101010100000 R
b10101010101010101010101010101000 7
b10101010101010101010101010101000 Y
b1010101010101010101010101010100 5
b1010101010101010101010101010100 `
b10101010101010101010101010101010 ,
b10101010101010101010101010101010 H
b10101010101010101010101010101010 N
b10101010101010101010101010101010 /
b10101010101010101010101010101010 O
b10101010101010101010101010101010 U
b10101010101010101010101010101010 .
b10101010101010101010101010101010 V
b10101010101010101010101010101010 \
b10101010101010101010101010101010 -
b10101010101010101010101010101010 ]
b10101010101010101010101010101010 c
b10101010101010101010101010101010 !
b10101010101010101010101010101010 +
b10101010101010101010101010101010 d
b11010101010101010101010101010101 :
b11010101010101010101010101010101 _
b11101010101010101010101010101010 <
b11101010101010101010101010101010 X
b11111010101010101010101010101010 =
b11111010101010101010101010101010 Q
b11111111101010101010101010101010 >
b11111111101010101010101010101010 J
0I
0P
0W
0^
0e
b10101010101010100000000000000000 1
b10101010101010100000000000000000 E
b10101010101010100000000000000000 F
b10101010101010101010101000000000 4
b10101010101010101010101000000000 L
b10101010101010101010101000000000 M
b10101010101010101010101010100000 3
b10101010101010101010101010100000 S
b10101010101010101010101010100000 T
b10101010101010101010101010101000 2
b10101010101010101010101010101000 Z
b10101010101010101010101010101000 [
b1010101010101010101010101010100 0
b1010101010101010101010101010100 a
b1010101010101010101010101010100 b
1B
b11111111111111111010101010101010 ;
b11111111111111111010101010101010 C
b1111111111111111 ?
b0 '
b0 A
0%
0@
1"
1)
b1 #
b0 &
b0 (
#6500
b1010101010101010101010101010100 !
b1010101010101010101010101010100 +
b1010101010101010101010101010100 d
1e
b1 '
b1 A
b1 (
