adder/rtl/pipeline_adder/fulladder1.v
module fulladder1(output sum,
				  output cout,
				  input a,
				  input b,
				  input cin
				 );
assign sum=a^b^cin;
assign cout=a&b | a&cin | b&cin;
endmodule

adder/rtl/pipeline_adder/fulladder4.v
module fulladder4(sum,cout,a,b,cin,clk);
output[3:0] sum;
output		cout;
input[3:0]	a;
input[3:0]	b;
input		cin;
input		clk;
reg[3:0] sum;
reg		 cout;
reg a0_reg,b0_reg,cin_reg;
reg a1_reg0,a1_reg1,b1_reg0,b1_reg1;
reg a2_reg0,a2_reg1,a2_reg2,b2_reg0,b2_reg1,b2_reg2;
reg a3_reg0,a3_reg1,a3_reg2,a3_reg3,b3_reg0,b3_reg1,b3_reg2,b3_reg3;
reg cout_reg0,cout_reg1,cout_reg2;
reg sum0_reg0,sum0_reg1,sum0_reg2;
reg sum1_reg0,sum1_reg1;
reg sum2_reg0;
wire sum0_wire,sum1_wire,sum2_wire,sum3_wire;
wire cout_wire0,cout_wire1,cout_wire2,cout_wire3;
//pipeline 1
always@(posedge clk)
	begin
		a0_reg<=a[0];
		b0_reg<=b[0];
		a1_reg0<=a[1];
		b1_reg0<=b[1];
		a2_reg0<=a[2];
		b2_reg0<=b[2];
		a3_reg0<=a[3];
		b3_reg0<=b[3];
		cin_reg<=cin;
	end
fulladder1 u0(sum0_wire,cout_wire0,a0_reg,b0_reg,cin_reg);
//pipeline 2
always@(posedge clk)
	begin
		a1_reg1<=a1_reg0;
		b1_reg1<=b1_reg0;
		a2_reg1<=a2_reg0;
		b2_reg1<=b2_reg0;
		a3_reg1<=a3_reg0;
		b3_reg1<=b3_reg0;
		cout_reg0<=cout_wire0;
		sum0_reg0<=sum0_wire;
	end
fulladder1 u1(sum1_wire,cout_wire1,a1_reg1,b1_reg1,cout_reg0);
//pipeline 3
always@(posedge clk)
	begin
		a2_reg2<=a2_reg1;
		b2_reg2<=b2_reg1;
		a3_reg2<=a3_reg1;
		b3_reg2<=b3_reg1;
		cout_reg1<=cout_wire1;
		sum1_reg0<=sum1_wire;
		sum0_reg1<=sum0_reg0;
	end
fulladder1 u2(sum2_wire,cout_wire2,a2_reg2,b2_reg2,cout_reg1);
//pipeline 4
always@(posedge clk)
	begin
		a3_reg3<=a3_reg2;
		b3_reg3<=b3_reg2;
		cout_reg2<=cout_wire2;
		sum2_reg0<=sum2_wire;
		sum1_reg1<=sum1_reg0;
		sum0_reg2<=sum0_reg1;
	end
fulladder1 u3(sum3_wire,cout_wire3,a3_reg3,b3_reg3,cout_reg2);
//pipeline 5
always@(posedge clk)
	begin
		cout<=cout_wire3;
		sum[3]<=sum3_wire;
		sum[2]<=sum2_reg0;
		sum[1]<=sum1_reg1;
		sum[0]<=sum0_reg2;
	end

endmodule

adder/bench/fulladder_tb1.v
`timescale 1ns/1ns
module fulladder_tb;
reg[3:0] a,b;
reg	cin;
reg	clk;
wire[3:0] sum;
wire[4:0] sum_all;
wire cout;
fulladder4 u0(.sum(sum),.cout(cout),.a(a),.b(b),.cin(cin),.clk(clk));
reg[4:0] a0,b0;
reg[1:0] cin0;
assign sum_all={cout,sum};
always #10 clk=~clk;
initial 
begin
	clk=0;
	for(cin0=0;cin0<=1'b1;cin0=cin0+1)
	begin
		cin=cin0[0];
		for(a0=5'b0;a0<=5'b1111;a0=a0+1)
		begin
			a=a0[3:0];
			for(b0=5'b0;b0<=5'b1111;b0=b0+1)
			begin	
				b=b0[3:0];
				@(negedge clk);
			end
		end
	end
	$finish;
end

initial
begin
	$dumpfile("../out/fulladder.vcd");
	$dumpvars;
end
endmodule

adder/sim/out/fulladder.vcd
$date
	Fri Jul 10 11:25:04 2015
$end
$version
	Icarus Verilog
$end
$timescale
	1ns
$end
$scope module fulladder_tb $end
$var wire 1 ! cout $end
$var wire 4 " sum [3:0] $end
$var wire 5 # sum_all [4:0] $end
$var reg 4 $ a [3:0] $end
$var reg 5 % a0 [4:0] $end
$var reg 4 & b [3:0] $end
$var reg 5 ' b0 [4:0] $end
$var reg 1 ( cin $end
$var reg 2 ) cin0 [1:0] $end
$var reg 1 * clk $end
$scope module u0 $end
$var wire 4 + a [3:0] $end
$var wire 4 , b [3:0] $end
$var wire 1 - cin $end
$var wire 1 . clk $end
$var wire 1 / cout_wire0 $end
$var wire 1 0 cout_wire1 $end
$var wire 1 1 cout_wire2 $end
$var wire 1 2 cout_wire3 $end
$var wire 1 3 sum0_wire $end
$var wire 1 4 sum1_wire $end
$var wire 1 5 sum2_wire $end
$var wire 1 6 sum3_wire $end
$var reg 1 7 a0_reg $end
$var reg 1 8 a1_reg0 $end
$var reg 1 9 a1_reg1 $end
$var reg 1 : a2_reg0 $end
$var reg 1 ; a2_reg1 $end
$var reg 1 < a2_reg2 $end
$var reg 1 = a3_reg0 $end
$var reg 1 > a3_reg1 $end
$var reg 1 ? a3_reg2 $end
$var reg 1 @ a3_reg3 $end
$var reg 1 A b0_reg $end
$var reg 1 B b1_reg0 $end
$var reg 1 C b1_reg1 $end
$var reg 1 D b2_reg0 $end
$var reg 1 E b2_reg1 $end
$var reg 1 F b2_reg2 $end
$var reg 1 G b3_reg0 $end
$var reg 1 H b3_reg1 $end
$var reg 1 I b3_reg2 $end
$var reg 1 J b3_reg3 $end
$var reg 1 K cin_reg $end
$var reg 1 L cout $end
$var reg 1 M cout_reg0 $end
$var reg 1 N cout_reg1 $end
$var reg 1 O cout_reg2 $end
$var reg 4 P sum [3:0] $end
$var reg 1 Q sum0_reg0 $end
$var reg 1 R sum0_reg1 $end
$var reg 1 S sum0_reg2 $end
$var reg 1 T sum1_reg0 $end
$var reg 1 U sum1_reg1 $end
$var reg 1 V sum2_reg0 $end
$scope module u0 $end
$var wire 1 W a $end
$var wire 1 X b $end
$var wire 1 Y cin $end
$var wire 1 / cout $end
$var wire 1 3 sum $end
$upscope $end
$scope module u1 $end
$var wire 1 Z a $end
$var wire 1 [ b $end
$var wire 1 \ cin $end
$var wire 1 0 cout $end
$var wire 1 4 sum $end
$upscope $end
$scope module u2 $end
$var wire 1 ] a $end
$var wire 1 ^ b $end
$var wire 1 _ cin $end
$var wire 1 1 cout $end
$var wire 1 5 sum $end
$upscope $end
$scope module u3 $end
$var wire 1 ` a $end
$var wire 1 a b $end
$var wire 1 b cin $end
$var wire 1 2 cout $end
$var wire 1 6 sum $end
$upscope $end
$upscope $end
$upscope $end
$enddefinitions $end
#0
$dumpvars
xb
xa
x`
x_
x^
x]
x\
x[
xZ
xY
xX
xW
xV
xU
xT
xS
xR
xQ
bx P
xO
xN
xM
xL
xK
xJ
xI
xH
xG
xF
xE
xD
xC
xB
xA
x@
x?
x>
x=
x<
x;
x:
x9
x8
x7
x6
x5
x4
x3
x2
x1
x0
x/
0.
0-
b0 ,
b0 +
0*
b0 )
0(
b0 '
b0 &
b0 %
b0 $
bx #
bx "
x!
$end
#10
0/
03
0K
0Y
0G
0=
0D
0:
0B
08
0A
0X
07
0W
bx P
1*
1.
#20
b1 &
b1 ,
b1 '
0*
0.
#30
00
13
04
bx P
0Q
0M
0\
0H
0>
0E
0;
0C
0[
09
0Z
1A
1X
1*
1.
#40
b10 &
b10 ,
b10 '
0*
0.
#50
03
01
05
1B
0A
0X
1Q
0R
0T
0N
0_
0I
0?
0F
0^
0<
0]
bx P
1*
1.
#60
b11 &
b11 ,
b11 '
0*
0.
#70
02
14
13
06
bx P
0S
0U
0V
0O
0b
0J
0a
0@
0`
1R
0Q
1C
1[
1A
1X
1*
1.
#80
b100 &
b100 ,
b100 '
0*
0.
#90
03
1D
0B
0A
0X
1Q
0R
1T
1S
b0 P
b0 "
0L
b0 #
0!
1*
1.
#100
b101 &
b101 ,
b101 '
0*
0.
#110
04
13
b1 #
b1 "
b1 P
0S
1U
1R
0Q
1E
0C
0[
1A
1X
1*
1.
#120
b110 &
b110 ,
b110 '
0*
0.
#130
03
15
1B
0A
0X
1Q
0R
0T
1F
1^
1S
b10 #
b10 "
b10 P
1*
1.
#140
b111 &
b111 ,
b111 '
0*
0.
#150
14
13
b11 #
b11 "
b11 P
0S
0U
1V
1R
0Q
1C
1[
1A
1X
1*
1.
#160
b1000 &
b1000 ,
b1000 '
0*
0.
#170
03
1G
0D
0B
0A
0X
1Q
0R
1T
1S
b100 #
b100 "
b100 P
1*
1.
#180
b1001 &
b1001 ,
b1001 '
0*
0.
#190
04
13
b101 #
b101 "
b101 P
0S
1U
1R
0Q
1H
0E
0C
0[
1A
1X
1*
1.
#200
b1010 &
b1010 ,
b1010 '
0*
0.
#210
03
05
1B
0A
0X
1Q
0R
0T
1I
0F
0^
1S
b110 #
b110 "
b110 P
1*
1.
#220
b1011 &
b1011 ,
b1011 '
0*
0.
#230
16
14
13
b111 #
b111 "
b111 P
0S
0U
0V
1J
1a
1R
0Q
1C
1[
1A
1X
1*
1.
#240
b1100 &
b1100 ,
b1100 '
0*
0.
#250
03
1D
0B
0A
0X
1Q
0R
1T
1S
b1000 P
b1000 #
b1000 "
1*
1.
#260
b1101 &
b1101 ,
b1101 '
0*
0.
#270
04
13
b1001 #
b1001 "
b1001 P
0S
1U
1R
0Q
1E
0C
0[
1A
1X
1*
1.
#280
b1110 &
b1110 ,
b1110 '
0*
0.
#290
03
15
1B
0A
0X
1Q
0R
0T
1F
1^
1S
b1010 #
b1010 "
b1010 P
1*
1.
#300
b1111 &
b1111 ,
b1111 '
0*
0.
#310
14
13
b1011 #
b1011 "
b1011 P
0S
0U
1V
1R
0Q
1C
1[
1A
1X
1*
1.
#320
b0 &
b0 ,
b1 $
b1 +
b1 %
b0 '
0*
0.
#330
0G
0D
0B
0A
0X
17
1W
1Q
0R
1T
1S
b1100 #
b1100 "
b1100 P
1*
1.
#340
b1 &
b1 ,
b1 '
0*
0.
#350
1/
04
03
b1101 #
b1101 "
b1101 P
0S
1U
1R
0H
0E
0C
0[
1A
1X
1*
1.
#360
b10 &
b10 ,
b10 '
0*
0.
#370
0/
13
05
14
1B
0A
0X
0Q
1M
1\
0T
0I
0F
0^
1S
b1110 #
b1110 "
b1110 P
1*
1.
#380
b11 &
b11 ,
b11 '
0*
0.
#390
1/
06
03
b1111 #
b1111 "
b1111 P
0U
0V
0J
0a
0R
1T
1Q
0M
0\
1C
1[
1A
1X
1*
1.
#400
b100 &
b100 ,
b100 '
0*
0.
#410
0/
13
10
04
1D
0B
0A
0X
0Q
1M
1\
1R
0S
1U
b1 P
b1 #
b1 "
1*
1.
#420
b101 &
b101 ,
b101 '
0*
0.
#430
1/
00
03
15
b10 #
b10 "
b10 P
1S
0R
0T
1N
1_
1Q
0M
0\
1E
0C
0[
1A
1X
1*
1.
#440
b110 &
b110 ,
b110 '
0*
0.
#450
0/
13
14
1B
0A
0X
0Q
1M
1\
1R
0N
0_
1F
1^
0S
0U
1V
b11 #
b11 "
b11 P
1*
1.
#460
b111 &
b111 ,
b111 '
0*
0.
#470
1/
03
b100 #
b100 "
b100 P
1S
0R
1T
1Q
0M
0\
1C
1[
1A
1X
1*
1.
#480
b1000 &
b1000 ,
b1000 '
0*
0.
#490
0/
13
10
04
1G
0D
0B
0A
0X
0Q
1M
1\
1R
0S
1U
b101 #
b101 "
b101 P
1*
1.
#500
b1001 &
b1001 ,
b1001 '
0*
0.
#510
1/
11
00
03
05
b110 #
b110 "
b110 P
1S
0R
0T
1N
1_
1Q
0M
0\
1H
0E
0C
0[
1A
1X
1*
1.
#520
b1010 &
b1010 ,
b1010 '
0*
0.
#530
0/
13
01
14
16
1B
0A
0X
0Q
1M
1\
1R
0N
0_
1I
0F
0^
0S
0U
0V
1O
1b
b111 #
b111 "
b111 P
1*
1.
#540
b1011 &
b1011 ,
b1011 '
0*
0.
#550
1/
03
b1000 P
b1000 #
b1000 "
1S
0O
0b
1J
1a
0R
1T
1Q
0M
0\
1C
1[
1A
1X
1*
1.
#560
b1100 &
b1100 ,
b1100 '
0*
0.
#570
0/
13
10
04
1D
0B
0A
0X
0Q
1M
1\
1R
0S
1U
b1001 #
b1001 "
b1001 P
1*
1.
#580
b1101 &
b1101 ,
b1101 '
0*
0.
#590
1/
00
03
15
b1010 #
b1010 "
b1010 P
1S
0R
0T
1N
1_
1Q
0M
0\
1E
0C
0[
1A
1X
1*
1.
#600
b1110 &
b1110 ,
b1110 '
0*
0.
#610
0/
13
14
1B
0A
0X
0Q
1M
1\
1R
0N
0_
1F
1^
0S
0U
1V
b1011 #
b1011 "
b1011 P
1*
1.
#620
b1111 &
b1111 ,
b1111 '
0*
0.
#630
1/
03
b1100 #
b1100 "
b1100 P
1S
0R
1T
1Q
0M
0\
1C
1[
1A
1X
1*
1.
#640
b0 &
b0 ,
b10 $
b10 +
b10 %
b0 '
0*
0.
#650
0/
10
04
0G
0D
0B
18
0A
0X
07
0W
0Q
1M
1\
1R
0S
1U
b1101 #
b1101 "
b1101 P
1*
1.
#660
b1 &
b1 ,
b1 '
0*
0.
#670
11
00
13
05
14
b1110 #
b1110 "
b1110 P
1S
0R
0T
1N
1_
0M
0\
0H
0E
0C
0[
19
1Z
1A
1X
1*
1.
#680
b10 &
b10 ,
b10 '
0*
0.
#690
03
01
12
06
1B
0A
0X
1Q
1T
0N
0_
0I
0F
0^
0S
0U
0V
1O
1b
b1111 #
b1111 "
b1111 P
1*
1.
#700
b11 &
b11 ,
b11 '
0*
0.
#710
10
02
04
13
b0 P
b0 "
1L
b10000 #
1!
1U
0O
0b
0J
0a
1R
0Q
1C
1[
1A
1X
1*
1.
#720
b100 &
b100 ,
b100 '
0*
0.
#730
03
15
1D
0B
0A
0X
1Q
0R
0T
1N
1_
1S
b10 "
b10 P
0L
b10 #
0!
1*
1.
#740
b101 &
b101 ,
b101 '
0*
0.
#750
00
14
13
b11 #
b11 "
b11 P
0S
0U
1V
1R
0Q
1E
0C
0[
1A
1X
1*
1.
#760
b110 &
b110 ,
b110 '
0*
0.
#770
03
1B
0A
0X
1Q
0R
1T
0N
0_
1F
1^
1S
b100 #
b100 "
b100 P
1*
1.
#780
b111 &
b111 ,
b111 '
0*
0.
#790
10
04
13
b101 #
b101 "
b101 P
0S
1U
1R
0Q
1C
1[
1A
1X
1*
1.
#800
b1000 &
b1000 ,
b1000 '
0*
0.
#810
03
11
05
1G
0D
0B
0A
0X
1Q
0R
0T
1N
1_
1S
b110 #
b110 "
b110 P
1*
1.
#820
b1001 &
b1001 ,
b1001 '
0*
0.
#830
00
14
13
16
b111 #
b111 "
b111 P
0S
0U
0V
1O
1b
1R
0Q
1H
0E
0C
0[
1A
1X
1*
1.
#840
b1010 &
b1010 ,
b1010 '
0*
0.
#850
03
01
1B
0A
0X
1Q
0R
1T
0N
0_
1I
0F
0^
1S
b1000 P
b1000 #
b1000 "
1*
1.
#860
b1011 &
b1011 ,
b1011 '
0*
0.
#870
10
04
13
b1001 #
b1001 "
b1001 P
0S
1U
0O
0b
1J
1a
1R
0Q
1C
1[
1A
1X
1*
1.
#880
b1100 &
b1100 ,
b1100 '
0*
0.
#890
03
15
1D
0B
0A
0X
1Q
0R
0T
1N
1_
1S
b1010 #
b1010 "
b1010 P
1*
1.
#900
b1101 &
b1101 ,
b1101 '
0*
0.
#910
00
14
13
b1011 #
b1011 "
b1011 P
0S
0U
1V
1R
0Q
1E
0C
0[
1A
1X
1*
1.
#920
b1110 &
b1110 ,
b1110 '
0*
0.
#930
03
1B
0A
0X
1Q
0R
1T
0N
0_
1F
1^
1S
b1100 #
b1100 "
b1100 P
1*
1.
#940
b1111 &
b1111 ,
b1111 '
0*
0.
#950
10
04
13
b1101 #
b1101 "
b1101 P
0S
1U
1R
0Q
1C
1[
1A
1X
1*
1.
#960
b0 &
b0 ,
b11 $
b11 +
b11 %
b0 '
0*
0.
#970
11
05
0G
0D
0B
0A
0X
17
1W
1Q
0R
0T
1N
1_
1S
b1110 #
b1110 "
b1110 P
1*
1.
#980
b1 &
b1 ,
b1 '
0*
0.
#990
00
1/
12
14
03
06
b1111 #
b1111 "
b1111 P
0S
0U
0V
1O
1b
1R
0H
0E
0C
0[
1A
1X
1*
1.
#1000
b10 &
b10 ,
b10 '
0*
0.
#1010
0/
10
13
01
04
1B
0A
0X
0Q
1M
1\
1T
0N
0_
0I
0F
0^
1S
b0 P
b0 "
1L
b10000 #
1!
1*
1.
#1020
b11 &
b11 ,
b11 '
0*
0.
#1030
1/
02
03
15
b10001 #
b1 "
b1 P
1U
0O
0b
0J
0a
0R
0T
1N
1_
1Q
0M
0\
1C
1[
1A
1X
1*
1.
#1040
b100 &
b100 ,
b100 '
0*
0.
#1050
0/
13
14
1D
0B
0A
0X
0Q
1M
1\
1R
0S
0U
1V
b11 "
b11 P
0L
b11 #
0!
1*
1.
#1060
b101 &
b101 ,
b101 '
0*
0.
#1070
00
1/
03
b100 #
b100 "
b100 P
1S
0R
1T
1Q
0M
0\
1E
0C
0[
1A
1X
1*
1.
#1080
b110 &
b110 ,
b110 '
0*
0.
#1090
0/
10
13
04
1B
0A
0X
0Q
1M
1\
1R
0N
0_
1F
1^
0S
1U
b101 #
b101 "
b101 P
1*
1.
#1100
b111 &
b111 ,
b111 '
0*
0.
#1110
1/
11
03
05
b110 #
b110 "
b110 P
1S
0R
0T
1N
1_
1Q
0M
0\
1C
1[
1A
1X
1*
1.
#1120
b1000 &
b1000 ,
b1000 '
0*
0.
#1130
0/
13
14
16
1G
0D
0B
0A
0X
0Q
1M
1\
1R
0S
0U
0V
1O
1b
b111 #
b111 "
b111 P
1*
1.
#1140
b1001 &
b1001 ,
b1001 '
0*
0.
#1150
00
1/
03
b1000 P
b1000 #
b1000 "
1S
0R
1T
1Q
0M
0\
1H
0E
0C
0[
1A
1X
1*
1.
#1160
b1010 &
b1010 ,
b1010 '
0*
0.
#1170
0/
10
13
01
04
1B
0A
0X
0Q
1M
1\
1R
0N
0_
1I
0F
0^
0S
1U
b1001 #
b1001 "
b1001 P
1*
1.
#1180
b1011 &
b1011 ,
b1011 '
0*
0.
#1190
1/
03
15
b1010 #
b1010 "
b1010 P
1S
0O
0b
1J
1a
0R
0T
1N
1_
1Q
0M
0\
1C
1[
1A
1X
1*
1.
#1200
b1100 &
b1100 ,
b1100 '
0*
0.
#1210
0/
13
14
1D
0B
0A
0X
0Q
1M
1\
1R
0S
0U
1V
b1011 #
b1011 "
b1011 P
1*
1.
#1220
b1101 &
b1101 ,
b1101 '
0*
0.
#1230
00
1/
03
b1100 #
b1100 "
b1100 P
1S
0R
1T
1Q
0M
0\
1E
0C
0[
1A
1X
1*
1.
#1240
b1110 &
b1110 ,
b1110 '
0*
0.
#1250
0/
10
13
04
1B
0A
0X
0Q
1M
1\
1R
0N
0_
1F
1^
0S
1U
b1101 #
b1101 "
b1101 P
1*
1.
#1260
b1111 &
b1111 ,
b1111 '
0*
0.
#1270
1/
11
03
05
b1110 #
b1110 "
b1110 P
1S
0R
0T
1N
1_
1Q
0M
0\
1C
1[
1A
1X
1*
1.
#1280
b0 &
b0 ,
b100 $
b100 +
b100 %
b0 '
0*
0.
#1290
0/
12
14
06
0G
0D
1:
0B
08
0A
0X
07
0W
0Q
1M
1\
1R
0S
0U
0V
1O
1b
b1111 #
b1111 "
b1111 P
1*
1.
#1300
b1 &
b1 ,
b1 '
0*
0.
#1310
00
13
04
b0 P
b0 "
1L
b10000 #
1!
1S
0R
1T
0M
0\
0H
0E
1;
0C
0[
09
0Z
1A
1X
1*
1.
#1320
b10 &
b10 ,
b10 '
0*
0.
#1330
03
01
15
1B
0A
0X
1Q
0T
0N
0_
0I
0F
0^
1<
1]
0S
1U
b10001 #
b1 "
b1 P
1*
1.
#1340
b11 &
b11 ,
b11 '
0*
0.
#1350
02
14
13
b10010 #
b10 "
b10 P
0U
1V
0O
0b
0J
0a
1R
0Q
1C
1[
1A
1X
1*
1.
#1360
b100 &
b100 ,
b100 '
0*
0.
#1370
03
1D
0B
0A
0X
1Q
0R
1T
1S
b100 "
b100 P
0L
b100 #
0!
1*
1.
#1380
b101 &
b101 ,
b101 '
0*
0.
#1390
04
13
b101 #
b101 "
b101 P
0S
1U
1R
0Q
1E
0C
0[
1A
1X
1*
1.
#1400
b110 &
b110 ,
b110 '
0*
0.
#1410
11
03
05
1B
0A
0X
1Q
0R
0T
1F
1^
1S
b110 #
b110 "
b110 P
1*
1.
#1420
b111 &
b111 ,
b111 '
0*
0.
#1430
14
13
16
b111 #
b111 "
b111 P
0S
0U
0V
1O
1b
1R
0Q
1C
1[
1A
1X
1*
1.
#1440
b1000 &
b1000 ,
b1000 '
0*
0.
#1450
03
1G
0D
0B
0A
0X
1Q
0R
1T
1S
b1000 P
b1000 #
b1000 "
1*
1.
#1460
b1001 &
b1001 ,
b1001 '
0*
0.
#1470
04
13
b1001 #
b1001 "
b1001 P
0S
1U
1R
0Q
1H
0E
0C
0[
1A
1X
1*
1.
#1480
b1010 &
b1010 ,
b1010 '
0*
0.
#1490
01
03
15
1B
0A
0X
1Q
0R
0T
1I
0F
0^
1S
b1010 #
b1010 "
b1010 P
1*
1.
#1500
b1011 &
b1011 ,
b1011 '
0*
0.
#1510
14
13
b1011 #
b1011 "
b1011 P
0S
0U
1V
0O
0b
1J
1a
1R
0Q
1C
1[
1A
1X
1*
1.
#1520
b1100 &
b1100 ,
b1100 '
0*
0.
#1530
03
1D
0B
0A
0X
1Q
0R
1T
1S
b1100 #
b1100 "
b1100 P
1*
1.
#1540
b1101 &
b1101 ,
b1101 '
0*
0.
#1550
04
13
b1101 #
b1101 "
b1101 P
0S
1U
1R
0Q
1E
0C
0[
1A
1X
1*
1.
#1560
b1110 &
b1110 ,
b1110 '
0*
0.
#1570
11
03
05
1B
0A
0X
1Q
0R
0T
1F
1^
1S
b1110 #
b1110 "
b1110 P
1*
1.
#1580
b1111 &
b1111 ,
b1111 '
0*
0.
#1590
12
14
13
06
b1111 #
b1111 "
b1111 P
0S
0U
0V
1O
1b
1R
0Q
1C
1[
1A
1X
1*
1.
#1600
b0 &
b0 ,
b101 $
b101 +
b101 %
b0 '
0*
0.
#1610
0G
0D
0B
0A
0X
17
1W
1Q
0R
1T
1S
b0 P
b0 "
1L
b10000 #
1!
1*
1.
#1620
b1 &
b1 ,
b1 '
0*
0.
#1630
1/
04
03
b10001 #
b1 "
b1 P
0S
1U
1R
0H
0E
0C
0[
1A
1X
1*
1.
#1640
b10 &
b10 ,
b10 '
0*
0.
#1650
0/
01
13
15
14
1B
0A
0X
0Q
1M
1\
0T
0I
0F
0^
1S
b10010 #
b10 "
b10 P
1*
1.
#1660
b11 &
b11 ,
b11 '
0*
0.
#1670
1/
02
03
b10011 #
b11 "
b11 P
0U
1V
0O
0b
0J
0a
0R
1T
1Q
0M
0\
1C
1[
1A
1X
1*
1.
#1680
b100 &
b100 ,
b100 '
0*
0.
#1690
0/
13
10
04
1D
0B
0A
0X
0Q
1M
1\
1R
0S
1U
b101 "
b101 P
0L
b101 #
0!
1*
1.
#1700
b101 &
b101 ,
b101 '
0*
0.
#1710
11
1/
00
03
05
b110 #
b110 "
b110 P
1S
0R
0T
1N
1_
1Q
0M
0\
1E
0C
0[
1A
1X
1*
1.
#1720
b110 &
b110 ,
b110 '
0*
0.
#1730
0/
13
14
16
1B
0A
0X
0Q
1M
1\
1R
0N
0_
1F
1^
0S
0U
0V
1O
1b
b111 #
b111 "
b111 P
1*
1.
#1740
b111 &
b111 ,
b111 '
0*
0.
#1750
1/
03
b1000 P
b1000 #
b1000 "
1S
0R
1T
1Q
0M
0\
1C
1[
1A
1X
1*
1.
#1760
b1000 &
b1000 ,
b1000 '
0*
0.
#1770
0/
13
10
04
1G
0D
0B
0A
0X
0Q
1M
1\
1R
0S
1U
b1001 #
b1001 "
b1001 P
1*
1.
#1780
b1001 &
b1001 ,
b1001 '
0*
0.
#1790
1/
00
03
15
b1010 #
b1010 "
b1010 P
1S
0R
0T
1N
1_
1Q
0M
0\
1H
0E
0C
0[
1A
1X
1*
1.
#1800
b1010 &
b1010 ,
b1010 '
0*
0.
#1810
0/
01
13
14
1B
0A
0X
0Q
1M
1\
1R
0N
0_
1I
0F
0^
0S
0U
1V
b1011 #
b1011 "
b1011 P
1*
1.
#1820
b1011 &
b1011 ,
b1011 '
0*
0.
#1830
1/
03
b1100 #
b1100 "
b1100 P
1S
0O
0b
1J
1a
0R
1T
1Q
0M
0\
1C
1[
1A
1X
1*
1.
#1840
b1100 &
b1100 ,
b1100 '
0*
0.
#1850
0/
13
10
04
1D
0B
0A
0X
0Q
1M
1\
1R
0S
1U
b1101 #
b1101 "
b1101 P
1*
1.
#1860
b1101 &
b1101 ,
b1101 '
0*
0.
#1870
11
1/
00
03
05
b1110 #
b1110 "
b1110 P
1S
0R
0T
1N
1_
1Q
0M
0\
1E
0C
0[
1A
1X
1*
1.
#1880
b1110 &
b1110 ,
b1110 '
0*
0.
#1890
0/
13
12
14
06
1B
0A
0X
0Q
1M
1\
1R
0N
0_
1F
1^
0S
0U
0V
1O
1b
b1111 #
b1111 "
b1111 P
1*
1.
#1900
b1111 &
b1111 ,
b1111 '
0*
0.
#1910
1/
03
b0 P
b0 "
1L
b10000 #
1!
1S
0R
1T
1Q
0M
0\
1C
1[
1A
1X
1*
1.
#1920
b0 &
b0 ,
b110 $
b110 +
b110 %
b0 '
0*
0.
#1930
0/
10
04
0G
0D
0B
18
0A
0X
07
0W
0Q
1M
1\
1R
0S
1U
b10001 #
b1 "
b1 P
1*
1.
#1940
b1 &
b1 ,
b1 '
0*
0.
#1950
00
13
15
14
b10010 #
b10 "
b10 P
1S
0R
0T
1N
1_
0M
0\
0H
0E
0C
0[
19
1Z
1A
1X
1*
1.
#1960
b10 &
b10 ,
b10 '
0*
0.
#1970
01
03
1B
0A
0X
1Q
1T
0N
0_
0I
0F
0^
0S
0U
1V
b10011 #
b11 "
b11 P
1*
1.
#1980
b11 &
b11 ,
b11 '
0*
0.
#1990
10
02
04
13
b10100 #
b100 "
b100 P
1U
0O
0b
0J
0a
1R
0Q
1C
1[
1A
1X
1*
1.
#2000
b100 &
b100 ,
b100 '
0*
0.
#2010
11
03
05
1D
0B
0A
0X
1Q
0R
0T
1N
1_
1S
b110 "
b110 P
0L
b110 #
0!
1*
1.
#2020
b101 &
b101 ,
b101 '
0*
0.
#2030
00
14
13
16
b111 #
b111 "
b111 P
0S
0U
0V
1O
1b
1R
0Q
1E
0C
0[
1A
1X
1*
1.
#2040
b110 &
b110 ,
b110 '
0*
0.
#2050
03
1B
0A
0X
1Q
0R
1T
0N
0_
1F
1^
1S
b1000 P
b1000 #
b1000 "
1*
1.
#2060
b111 &
b111 ,
b111 '
0*
0.
#2070
10
04
13
b1001 #
b1001 "
b1001 P
0S
1U
1R
0Q
1C
1[
1A
1X
1*
1.
#2080
b1000 &
b1000 ,
b1000 '
0*
0.
#2090
03
15
1G
0D
0B
0A
0X
1Q
0R
0T
1N
1_
1S
b1010 #
b1010 "
b1010 P
1*
1.
#2100
b1001 &
b1001 ,
b1001 '
0*
0.
#2110
00
14
13
b1011 #
b1011 "
b1011 P
0S
0U
1V
1R
0Q
1H
0E
0C
0[
1A
1X
1*
1.
#2120
b1010 &
b1010 ,
b1010 '
0*
0.
#2130
01
03
1B
0A
0X
1Q
0R
1T
0N
0_
1I
0F
0^
1S
b1100 #
b1100 "
b1100 P
1*
1.
#2140
b1011 &
b1011 ,
b1011 '
0*
0.
#2150
10
04
13
b1101 #
b1101 "
b1101 P
0S
1U
0O
0b
1J
1a
1R
0Q
1C
1[
1A
1X
1*
1.
#2160
b1100 &
b1100 ,
b1100 '
0*
0.
#2170
11
03
05
1D
0B
0A
0X
1Q
0R
0T
1N
1_
1S
b1110 #
b1110 "
b1110 P
1*
1.
#2180
b1101 &
b1101 ,
b1101 '
0*
0.
#2190
00
12
14
13
06
b1111 #
b1111 "
b1111 P
0S
0U
0V
1O
1b
1R
0Q
1E
0C
0[
1A
1X
1*
1.
#2200
b1110 &
b1110 ,
b1110 '
0*
0.
#2210
03
1B
0A
0X
1Q
0R
1T
0N
0_
1F
1^
1S
b0 P
b0 "
1L
b10000 #
1!
1*
1.
#2220
b1111 &
b1111 ,
b1111 '
0*
0.
#2230
10
04
13
b10001 #
b1 "
b1 P
0S
1U
1R
0Q
1C
1[
1A
1X
1*
1.
#2240
b0 &
b0 ,
b111 $
b111 +
b111 %
b0 '
0*
0.
#2250
15
0G
0D
0B
0A
0X
17
1W
1Q
0R
0T
1N
1_
1S
b10010 #
b10 "
b10 P
1*
1.
#2260
b1 &
b1 ,
b1 '
0*
0.
#2270
00
1/
14
03
b10011 #
b11 "
b11 P
0S
0U
1V
1R
0H
0E
0C
0[
1A
1X
1*
1.
#2280
b10 &
b10 ,
b10 '
0*
0.
#2290
0/
10
01
13
04
1B
0A
0X
0Q
1M
1\
1T
0N
0_
0I
0F
0^
1S
b10100 #
b100 "
b100 P
1*
1.
#2300
b11 &
b11 ,
b11 '
0*
0.
#2310
11
1/
02
03
05
b10101 #
b101 "
b101 P
1U
0O
0b
0J
0a
0R
0T
1N
1_
1Q
0M
0\
1C
1[
1A
1X
1*
1.
#2320
b100 &
b100 ,
b100 '
0*
0.
#2330
0/
13
14
16
1D
0B
0A
0X
0Q
1M
1\
1R
0S
0U
0V
1O
1b
b111 "
b111 P
0L
b111 #
0!
1*
1.
#2340
b101 &
b101 ,
b101 '
0*
0.
#2350
00
1/
03
b1000 P
b1000 #
b1000 "
1S
0R
1T
1Q
0M
0\
1E
0C
0[
1A
1X
1*
1.
#2360
b110 &
b110 ,
b110 '
0*
0.
#2370
0/
10
13
04
1B
0A
0X
0Q
1M
1\
1R
0N
0_
1F
1^
0S
1U
b1001 #
b1001 "
b1001 P
1*
1.
#2380
b111 &
b111 ,
b111 '
0*
0.
